{
  "meals": [
    {
      "id": "hm001",
      "name": "牛腩炖萝卜饭",
      "category": "自煮",
      "date": "2026-02",
      "rating": 0,
      "images": [
        "/images/homemake/hm001.jpg"
      ],
      "ingredients": [
        "牛腩",
        "胡萝卜",
        "油菜"
      ],
      "steps": [
        "牛腩焯水",
        "后烧新水加入牛腩和卤料；快熟的时候加入胡萝卜继续中小火炖30mins"
      ],
      "notes": "简单的午餐",
      "cuisine": "",
      "entry_date": "46087.0",
      "difficulty": 50,
      "makingTime": 40
    },
    {
      "id": "hm002",
      "name": "葱油拌面+叉烧和豌豆",
      "category": "自煮",
      "date": "2026-02",
      "rating": 0,
      "images": [
        "/images/homemake/hm002.jpg"
      ],
      "ingredients": [
        "细面条",
        "叉烧",
        "豌豆"
      ],
      "steps": [
        "先做好葱油（油小火加热后依次放入葱段 盐 酱油 香油）",
        "后放入煮熟的面条拌",
        "加热叉烧和豌豆"
      ],
      "notes": "简单的午餐",
      "cuisine": "",
      "entry_date": "",
      "difficulty": 30,
      "makingTime": 30
    },
    {
      "id": "hm003",
      "name": "麻辣火锅",
      "category": "自煮",
      "date": "2026-02",
      "rating": 0,
      "images": [
        "/images/homemake/hm003-1.jpg",
        "/images/homemake/hm003-2.jpg",
        "/images/homemake/hm003-3.jpg",
        "/images/homemake/hm003-4.jpg"
      ],
      "ingredients": [
        "牛肩肉",
        "羊肉",
        "自制虾滑（需用新鲜的虾）",
        "时蔬",
        "豆腐泡",
        "火锅底料"
      ],
      "steps": [
        "在烹饪区先提前加热好火锅底料和水",
        "放入难煮的东西",
        "全部弄好后移至移动煤气灶区"
      ],
      "notes": "随心火锅，冬天必备，不知道吃什么时必备",
      "cuisine": "",
      "entry_date": "",
      "difficulty": 0,
      "makingTime": 15
    },
    {
      "id": "hm004",
      "name": "nan",
      "category": "自煮",
      "date": "2026-02",
      "rating": 0,
      "images": [
        "/images/homemake/hm004.jpg"
      ],
      "ingredients": [],
      "steps": [],
      "notes": "",
      "cuisine": "",
      "entry_date": ""
    },
    {
      "id": "hm005",
      "name": "自家烧烤",
      "category": "自煮",
      "date": "2026-02",
      "rating": 0,
      "images": [
        "/images/homemake/hm005-1.jpg",
        "/images/homemake/hm005-2.jpg",
        "/images/homemake/hm005-3.jpg",
        "/images/homemake/hm005-4.jpg",
        "/images/homemake/hm005-5.jpg",
        ""
      ],
      "ingredients": [
        "牛肉片",
        "猪肉片",
        "鲜虾",
        "杏鲍菇",
        "午餐片"
      ],
      "steps": [
        "将牛肉先提前切好抹少许盐",
        "鲜虾挑掉虾线",
        "午餐片切5mm厚"
      ],
      "notes": "朋友聚餐最简单，又好吃又热闹",
      "cuisine": "",
      "entry_date": "",
      "difficulty": 20,
      "makingTime": 15
    },
    {
      "id": "hm006",
      "name": "过节晚餐",
      "category": "自煮",
      "date": "2026-02",
      "rating": 0,
      "images": [
        "/images/homemake/hm006-1.jpg",
        "/images/homemake/hm006-2.jpg",
        "/images/homemake/hm006-3.jpg",
        "/images/homemake/hm006-4.jpg",
        ""
      ],
      "ingredients": [
        "萝卜糕香芋糕（步步高升）",
        "豆苗菜",
        "鱼胶糯米甜汤圆",
        "板栗蒸排骨",
        "盐焗鸡",
        "三文鱼",
        "水饺",
        "油菜",
        "白葡萄酒"
      ],
      "steps": [
        "太复杂了"
      ],
      "notes": "过节8道菜",
      "cuisine": "",
      "entry_date": "",
      "difficulty": 60,
      "makingTime": 120
    },
    {
      "id": "hm007",
      "name": "酸菜鱼",
      "category": "自煮",
      "date": "2026-02",
      "rating": 0,
      "images": [
        "/images/homemake/hm007-1.jpg",
        "/images/homemake/hm007-2.jpg"
      ],
      "ingredients": [
        "黑鱼片",
        "芦笋",
        "时蔬",
        "腐竹",
        "豆腐"
      ],
      "steps": [
        "先把锅底加水加热好",
        "需要提前煮熟的食材用另外一个锅烧好",
        "加入味道锅一起煮",
        "后放蔬菜",
        "加热辣油",
        "泼上去"
      ],
      "notes": "味道基本跟外面一样呢，嘿嘿",
      "cuisine": "",
      "entry_date": "",
      "difficulty": 70,
      "makingTime": 40
    },
    {
      "id": "hm008",
      "name": "全蒸早餐",
      "category": "自煮",
      "date": "2026-02",
      "rating": 0,
      "images": [
        "/images/homemake/hm008-1.jpg",
        "/images/homemake/hm008-2.jpg"
      ],
      "ingredients": [
        "芋头包",
        "油菜",
        "鸡蛋",
        "板栗",
        "虾饺",
        "鹌鹑蛋"
      ],
      "steps": [
        "全部洗好",
        "摆上蒸架",
        "计时15mins"
      ],
      "notes": "懒人早餐，碳水偏多",
      "cuisine": "",
      "entry_date": "",
      "difficulty": 0,
      "makingTime": 15
    },
    {
      "id": "hm009",
      "name": "咖喱乌冬面",
      "category": "自煮",
      "date": "2026-02",
      "rating": 0,
      "images": [
        "/images/homemake/hm009-1.jpg",
        "/images/homemake/hm009-2.jpg",
        "/images/homemake/hm009-3.jpg",
        "/images/homemake/hm009-4.jpg",
        ""
      ],
      "ingredients": [
        "乌冬面",
        "虾",
        "咖喱粉",
        "土豆",
        "胡萝卜",
        "鸡肉块"
      ],
      "steps": [
        "土豆先四面煎",
        "鸡肉块也要煎",
        "虾炸好",
        "乌冬面焯水",
        "做好咖喱酱后放入土豆胡萝卜和鸡肉",
        "淋在乌冬面上",
        "炸虾可以沾咖喱酱"
      ],
      "notes": "咖喱酱可以一次性多煮一点，下一顿淋米饭也很美味哦",
      "cuisine": "",
      "entry_date": "",
      "difficulty": 80,
      "makingTime": 60
    },
    {
      "id": "rt001",
      "name": "popeyes炸鸡",
      "category": "餐厅",
      "date": "2025-02",
      "rating": 3.0,
      "images": [
        "/images/restaurant/rt001.jpg"
      ],
      "ingredients": [
        "肉酱薯条",
        "鸡肉卷",
        "炸鸡柳",
        "苹果派"
      ],
      "steps": [
        "由餐厅提供制作"
      ],
      "notes": "鸡肉卷不错，炸鸡胸肉条吃起来素素的，酱OK",
      "cuisine": "西式",
      "entry_date": "",
      "cost": 30.0
    },
    {
      "id": "rt002",
      "name": "自助火锅",
      "category": "餐厅",
      "date": "2025-02",
      "rating": 1.0,
      "images": [
        "/images/restaurant/rt002-1.jpg",
        "/images/restaurant/rt002-2.jpg"
      ],
      "ingredients": [
        "自选多样菜色",
        "麻辣锅底和清汤锅底"
      ],
      "steps": [
        "由餐厅提供制作"
      ],
      "notes": "锅底有一股中药味不是很喜欢，很多蒜头。中低端火锅店",
      "cuisine": "中式",
      "entry_date": "",
      "cost": 76.0
    },
    {
      "id": "rt003",
      "name": "越南粉",
      "category": "餐厅",
      "date": "2025-02",
      "rating": 3.0,
      "images": [
        "/images/restaurant/rt003.jpg"
      ],
      "ingredients": [
        "经典口味+鸡肉拌粉"
      ],
      "steps": [
        "由餐厅提供制作"
      ],
      "notes": "越南粉是不想吃上火的东西的时候，会第2个蹦出来的选项，基本款不会出错",
      "cuisine": "越南菜",
      "entry_date": "",
      "cost": 56.4
    },
    {
      "id": "rt004",
      "name": "Fiveguys汉堡包",
      "category": "餐厅",
      "date": "2025-02",
      "rating": 3.0,
      "images": [
        "/images/restaurant/rt004.jpg"
      ],
      "ingredients": [
        "培根牛肉汉堡包+必点薯条"
      ],
      "steps": [
        "由餐厅提供制作"
      ],
      "notes": "小size就够吃咯，自助花生很有意思，味道没有独立汉堡店好吃",
      "cuisine": "西餐",
      "entry_date": "",
      "cost": 32.7
    },
    {
      "id": "rt005",
      "name": "品一品麻辣香锅",
      "category": "餐厅",
      "date": "2025-02",
      "rating": 4.0,
      "images": [
        "/images/restaurant/rt005-1.jpg",
        "/images/restaurant/rt005-2.jpg"
      ],
      "ingredients": [
        "半只鸡+其他杂七杂八的配菜"
      ],
      "steps": [
        "由餐厅提供制作"
      ],
      "notes": "服务和味道都很在线，但是排队1个半小时+等待用餐50分钟让这顿饭时间性价比很低",
      "cuisine": "中式",
      "entry_date": "",
      "cost": 80.0
    },
    {
      "id": "to001",
      "name": "ChickenChicken炸鸡",
      "category": "外卖",
      "date": "2025-02",
      "rating": 3.0,
      "images": [
        "/images/takeout/to001-1.jpg",
        "/images/takeout/to001-2.jpg"
      ],
      "ingredients": [
        "3个口味的炸鸡"
      ],
      "steps": [
        "由餐厅提供制作"
      ],
      "notes": "还是最喜欢甜辣酱",
      "cuisine": "韩餐",
      "entry_date": "",
      "cost": 30.0
    },
    {
      "id": "to002",
      "name": "披萨",
      "category": "外卖",
      "date": "2025-01",
      "rating": 3.0,
      "images": [
        "/images/takeout/to002-1.jpg",
        "/images/takeout/to002-2.jpg",
        ""
      ],
      "ingredients": [
        "牛肉",
        "鸡肉",
        "菠萝"
      ],
      "steps": [
        "由餐厅提供制作"
      ],
      "notes": "披萨的味道，哈哈",
      "cuisine": "日式",
      "entry_date": "",
      "cost": 14.69
    },
    {
      "id": "to003",
      "name": "蜀庄四川料理",
      "category": "外卖",
      "date": "2025-02",
      "rating": 3.0,
      "images": [
        "/images/takeout/to003-1.jpg",
        "/images/takeout/to003-2.jpg",
        "/images/takeout/to003-3.jpg"
      ],
      "ingredients": [
        "沙爹牛肉",
        "蘑菇腰果杂炒；红油抄手"
      ],
      "steps": [
        "由餐厅提供制作"
      ],
      "notes": "味道正常",
      "cuisine": "中餐",
      "entry_date": "",
      "cost": 25.0
    },
    {
      "id": "to004",
      "name": "蜀味四川料理",
      "category": "外卖",
      "date": "2025-02",
      "rating": 2.0,
      "images": [
        "/images/takeout/to004-1.jpg",
        "/images/takeout/to004-2.jpg",
        "/images/takeout/to004-3.jpg"
      ],
      "ingredients": [
        "炸猪排",
        "口水鸡",
        "麻辣香锅"
      ],
      "steps": [
        "由餐厅提供制作"
      ],
      "notes": "炸猪排还行;但是口水鸡和麻辣香锅一般般",
      "cuisine": "中餐",
      "entry_date": "",
      "cost": 25.0
    },
    {
      "id": "to005",
      "name": "Subway三明治",
      "category": "外卖",
      "date": "2025-02",
      "rating": 4.0,
      "images": [
        "/images/takeout/to005.jpg"
      ],
      "ingredients": [
        "牛肉碎粗粮面包三明治x2"
      ],
      "steps": [
        "由餐厅提供制作"
      ],
      "notes": "喜欢里面脆脆的炸洋葱",
      "cuisine": "西式",
      "entry_date": "",
      "cost": 14.48
    },
    {
      "id": "bd001",
      "name": "鸭胸肉油菜+春卷卤肉饭",
      "category": "便当",
      "date": "2026-01",
      "rating": 4.0,
      "images": [
        "/images/convenient/bd001.jpg"
      ],
      "ingredients": [
        "花生米饭",
        "鸭胸肉",
        "油菜",
        "春卷",
        "卤肉"
      ],
      "steps": [
        "准备便当盒，铺上米饭",
        "烤箱加热春卷和鸭胸肉",
        "焯油菜花",
        "微波炉加热卤肉",
        "先摆肉再摆菜"
      ],
      "notes": "有点过于丰富的午餐便当...",
      "cuisine": "中餐",
      "entry_date": "",
      "difficulty": 60,
      "makingTime": 30
    },
    {
      "id": "bd002",
      "name": "汉堡肉饭",
      "category": "便当",
      "date": "2026-01",
      "rating": 4.0,
      "images": [
        "/images/convenient/bd002-1.jpg",
        "/images/convenient/bd002-2.jpg",
        "/images/convenient/bd002-3.jpg",
        "/images/convenient/bd002-4.jpg"
      ],
      "ingredients": [
        "牛肉碎",
        "奶白菜",
        "皮蛋咸鸭蛋",
        "鸡蛋"
      ],
      "steps": [
        "用厨师机制作汉堡肉",
        "摔出圆球形状放锅里煎",
        "先下双蛋后下奶白菜炒",
        "煎鸡蛋",
        "摆盘"
      ],
      "notes": "虽然制作汉堡肉很麻烦, 但制作一次之后放冰箱可以吃很多次哦",
      "cuisine": "中&日",
      "entry_date": "",
      "difficulty": 80,
      "makingTime": 70
    },
    {
      "id": "bd003",
      "name": "香菇蒸鸡+胡萝卜炒腐竹饭",
      "category": "便当",
      "date": "2026-01",
      "rating": 4.0,
      "images": [
        "/images/convenient/bd003-1.jpg",
        "/images/convenient/bd003-2.jpg"
      ],
      "ingredients": [
        "米饭",
        "鸡腿肉",
        "香菇x5",
        "胡萝卜",
        "白菜",
        "腐竹"
      ],
      "steps": [
        "将泡好的香菇和腌好的鸡腿肉一起放进高压锅米饭煮",
        "胡萝卜先炒,后下白菜和腐竹",
        "米饭煮好,把鸡胸肉夹出来",
        "摆盘"
      ],
      "notes": "用米饭高压锅一起煮一道菜实质是利用里面的蒸汽,偷懒的好办法哦",
      "cuisine": "中餐",
      "entry_date": "",
      "difficulty": 40,
      "makingTime": 30
    },
    {
      "id": "bd004",
      "name": "西兰花鱼饼饭",
      "category": "便当",
      "date": "2026-01",
      "rating": 4.0,
      "images": [
        "/images/convenient/bd004.jpg"
      ],
      "ingredients": [
        "米饭",
        "西兰花",
        "鱼饼",
        "午餐肉",
        "鸡蛋"
      ],
      "steps": [
        "准备便当盒，铺上米饭",
        "先煎好午餐肉,再炒西兰花",
        "煎熟鱼饼和鸡蛋",
        "炒一些豆腐干和黑木耳进去一起",
        "先摆肉再摆菜"
      ],
      "notes": "西兰花是点缀便当的好食材",
      "cuisine": "中餐",
      "entry_date": "",
      "difficulty": 40,
      "makingTime": 35
    },
    {
      "id": "bd005",
      "name": "火腿肠肉松豌豆饭团",
      "category": "便当",
      "date": "2026-01",
      "rating": 4.0,
      "images": [
        "/images/convenient/bd005-1.jpg",
        "/images/convenient/bd005-2.jpg",
        "/images/convenient/bd005-3.jpg",
        "/images/convenient/bd005-4.jpg",
        "/images/convenient/bd005-5.jpg"
      ],
      "ingredients": [
        "白米,紫米,糯米5:3:2",
        "火腿肠1根",
        "熏牛胸肉",
        "灵魂咸鸭蛋黄",
        "肉松",
        "豌豆"
      ],
      "steps": [
        "铺上保鲜膜,把饭盛碗里,倒在保鲜膜上铺平",
        "先放入肉松铺平",
        "再依次放入喜爱的食材",
        "先把上下2端合起来,用手裹紧竹帘",
        "利用保鲜膜两端绕紧,最后用双手调整,对半切"
      ],
      "notes": "方便快捷的饭团,非常适合准备好带出门吃",
      "cuisine": "日式",
      "entry_date": "",
      "difficulty": 30,
      "makingTime": 20
    },
    {
      "id": "bd006",
      "name": "熏肉片金枪鱼牛油果肉松饭团",
      "category": "便当",
      "date": "2026-01",
      "rating": 4.0,
      "images": [
        "/images/convenient/bd006-1.jpg",
        "/images/convenient/bd006-2.jpg",
        "/images/convenient/bd006-3.jpg",
        "/images/convenient/bd006-4.jpg",
        "/images/convenient/bd006-5.jpg"
      ],
      "ingredients": [
        "白米,紫米,糯米5:3:2",
        "熏肉片",
        "肉松",
        "金枪鱼罐头",
        "牛油果半颗"
      ],
      "steps": [
        "铺上保鲜膜,把饭盛碗里,倒在保鲜膜上铺平",
        "先放入肉松铺平",
        "再依次放入喜爱的食材",
        "先把上下2端合起来,用手裹紧竹帘",
        "利用保鲜膜两端绕紧,最后用双手调整,对半切"
      ],
      "notes": "方便快捷的饭团,非常适合准备好带出门吃",
      "cuisine": "日式",
      "entry_date": "",
      "difficulty": 30,
      "makingTime": 20
    },
    {
      "id": "bk001",
      "name": "Kiwi奥利奥慕斯蛋糕",
      "category": "Bakery",
      "date": "2025-03",
      "rating": 5.0,
      "images": [
        "/images/bakery/bk001.jpg"
      ],
      "ingredients": [
        "糖 150g",
        "牛奶 400ml",
        "淡奶油 200ml",
        "鸡蛋 3个",
        "香草精"
      ],
      "steps": [
        "制作焦糖液倒入布丁杯",
        "加热牛奶和奶油",
        "鸡蛋打发加糖",
        "混合混合物",
        "水浴烤40分钟",
        "冷藏4小时"
      ],
      "notes": "口感软糯，黑芝麻香气十足，很解馋",
      "cuisine": "甜点",
      "entry_date": "",
      "difficulty": 80,
      "makingTime": 45
    },
    {
      "id": "bk002",
      "name": "抹茶提拉米苏",
      "category": "Bakery",
      "date": "2025-01",
      "rating": 5.0,
      "images": [
        "/images/bakery/bk002.jpg"
      ],
      "ingredients": [
        "糖 150g",
        "牛奶 400ml",
        "淡奶油 200ml",
        "鸡蛋 3个",
        "香草精"
      ],
      "steps": [
        "制作焦糖液倒入布丁杯",
        "加热牛奶和奶油",
        "鸡蛋打发加糖",
        "混合混合物",
        "水浴烤40分钟",
        "冷藏4小时"
      ],
      "notes": "抹茶的清香和芝士的浓郁完美融合，甜度刚好",
      "cuisine": "甜点",
      "entry_date": "",
      "difficulty": 80,
      "makingTime": 60
    },
    {
      "id": "bk003",
      "name": "榴莲千层蛋糕",
      "category": "Bakery",
      "date": "2025-01",
      "rating": 5.0,
      "images": [
        "/images/bakery/bk003.jpg"
      ],
      "ingredients": [
        "糖 150g",
        "牛奶 400ml",
        "淡奶油 200ml",
        "鸡蛋 3个",
        "香草精"
      ],
      "steps": [
        "制作焦糖液倒入布丁杯",
        "加热牛奶和奶油",
        "鸡蛋打发加糖",
        "混合混合物",
        "水浴烤40分钟",
        "冷藏4小时"
      ],
      "notes": "榴莲的王道吃法！尽管价格贵但真的值得",
      "cuisine": "甜点",
      "entry_date": "",
      "difficulty": 80,
      "makingTime": 90
    },
    {
      "id": "bk004",
      "name": "草莓芝士蛋糕",
      "category": "Bakery",
      "date": "2025-02",
      "rating": 4.5,
      "images": [
        "/images/bakery/bk004.jpg"
      ],
      "ingredients": [
        "糖 150g",
        "牛奶 400ml",
        "淡奶油 200ml",
        "鸡蛋 3个",
        "香草精"
      ],
      "steps": [
        "制作焦糖液倒入布丁杯",
        "加热牛奶和奶油",
        "鸡蛋打发加糖",
        "混合混合物",
        "水浴烤40分钟",
        "冷藏4小时"
      ],
      "notes": "酸甜适中，奶油感十足，草莓新鲜又漂亮",
      "cuisine": "甜点",
      "entry_date": "",
      "difficulty": 80,
      "makingTime": 75
    },
    {
      "id": "bk005",
      "name": "巧克力熔浆蛋糕",
      "category": "Bakery",
      "date": "2025-02",
      "rating": 5.0,
      "images": [
        "/images/bakery/bk005.jpg"
      ],
      "ingredients": [
        "糖 150g",
        "牛奶 400ml",
        "淡奶油 200ml",
        "鸡蛋 3个",
        "香草精"
      ],
      "steps": [
        "制作焦糖液倒入布丁杯",
        "加热牛奶和奶油",
        "鸡蛋打发加糖",
        "混合混合物",
        "水浴烤40分钟",
        "冷藏4小时"
      ],
      "notes": "切开时巧克力浆缓缓流出，绝对的诱人甜蜜",
      "cuisine": "甜点",
      "entry_date": "",
      "difficulty": 80,
      "makingTime": 40
    },
    {
      "id": "bk006",
      "name": "巧克力熔浆蛋糕",
      "category": "Bakery",
      "date": "2025-02",
      "rating": 5.0,
      "images": [
        "/images/bakery/bk006.jpg"
      ],
      "ingredients": [
        "糖 150g",
        "牛奶 400ml",
        "淡奶油 200ml",
        "鸡蛋 3个",
        "香草精"
      ],
      "steps": [
        "同上"
      ],
      "notes": "经典的甜蜜诱惑",
      "cuisine": "甜点",
      "entry_date": "",
      "difficulty": 80,
      "makingTime": 40
    },
    {
      "id": "bk007",
      "name": "巧克力熔浆蛋糕",
      "category": "Bakery",
      "date": "2025-02",
      "rating": 5.0,
      "images": [
        "/images/bakery/bk007.jpg"
      ],
      "ingredients": [
        "糖 150g",
        "牛奶 400ml",
        "淡奶油 200ml",
        "鸡蛋 3个",
        "香草精"
      ],
      "steps": [
        "同上"
      ],
      "notes": "经典的甜蜜诱惑",
      "cuisine": "甜点",
      "entry_date": "",
      "difficulty": 80,
      "makingTime": 40
    },
    {
      "id": "bk008",
      "name": "巧克力熔浆蛋糕",
      "category": "Bakery",
      "date": "2025-02",
      "rating": 5.0,
      "images": [
        "/images/bakery/bk008.jpg"
      ],
      "ingredients": [
        "糖 150g",
        "牛奶 400ml",
        "淡奶油 200ml",
        "鸡蛋 3个",
        "香草精"
      ],
      "steps": [
        "同上"
      ],
      "notes": "经典的甜蜜诱惑",
      "cuisine": "甜点",
      "entry_date": "",
      "difficulty": 80,
      "makingTime": 40
    },
    {
      "id": "bk009",
      "name": "巧克力熔浆蛋糕",
      "category": "Bakery",
      "date": "2025-02",
      "rating": 5.0,
      "images": [
        "/images/bakery/bk009.jpg"
      ],
      "ingredients": [
        "糖 150g",
        "牛奶 400ml",
        "淡奶油 200ml",
        "鸡蛋 3个",
        "香草精"
      ],
      "steps": [
        "同上"
      ],
      "notes": "经典的甜蜜诱惑",
      "cuisine": "甜点",
      "entry_date": "",
      "difficulty": 80,
      "makingTime": 40
    },
    {
      "id": "bk010",
      "name": "巧克力熔浆蛋糕",
      "category": "Bakery",
      "date": "2025-02",
      "rating": 5.0,
      "images": [
        "/images/bakery/bk010.jpg"
      ],
      "ingredients": [
        "糖 150g",
        "牛奶 400ml",
        "淡奶油 200ml",
        "鸡蛋 3个",
        "香草精"
      ],
      "steps": [
        "同上"
      ],
      "notes": "经典的甜蜜诱惑",
      "cuisine": "甜点",
      "entry_date": "",
      "difficulty": 80,
      "makingTime": 40
    },
    {
      "id": "bk011",
      "name": "巧克力熔浆蛋糕",
      "category": "Bakery",
      "date": "2025-02",
      "rating": 5.0,
      "images": [
        "/images/bakery/bk011.jpg"
      ],
      "ingredients": [
        "糖 150g",
        "牛奶 400ml",
        "淡奶油 200ml",
        "鸡蛋 3个",
        "香草精"
      ],
      "steps": [
        "同上"
      ],
      "notes": "经典的甜蜜诱惑",
      "cuisine": "甜点",
      "entry_date": "",
      "difficulty": 80,
      "makingTime": 40
    },
    {
      "id": "bk012",
      "name": "巧克力熔浆蛋糕",
      "category": "Bakery",
      "date": "2025-02",
      "rating": 5.0,
      "images": [
        "/images/bakery/bk012.jpg"
      ],
      "ingredients": [
        "糖 150g",
        "牛奶 400ml",
        "淡奶油 200ml",
        "鸡蛋 3个",
        "香草精"
      ],
      "steps": [
        "同上"
      ],
      "notes": "经典的甜蜜诱惑",
      "cuisine": "甜点",
      "entry_date": "",
      "difficulty": 80,
      "makingTime": 40
    },
    {
      "id": "bk013",
      "name": "巧克力熔浆蛋糕",
      "category": "Bakery",
      "date": "2025-02",
      "rating": 5.0,
      "images": [
        "/images/bakery/bk013.jpg"
      ],
      "ingredients": [
        "糖 150g",
        "牛奶 400ml",
        "淡奶油 200ml",
        "鸡蛋 3个",
        "香草精"
      ],
      "steps": [
        "同上"
      ],
      "notes": "经典的甜蜜诱惑",
      "cuisine": "甜点",
      "entry_date": "",
      "difficulty": 80,
      "makingTime": 40
    },
    {
      "id": "bk014",
      "name": "巧克力熔浆蛋糕",
      "category": "Bakery",
      "date": "2025-02",
      "rating": 5.0,
      "images": [
        "/images/bakery/bk014.jpg"
      ],
      "ingredients": [
        "糖 150g",
        "牛奶 400ml",
        "淡奶油 200ml",
        "鸡蛋 3个",
        "香草精"
      ],
      "steps": [
        "同上"
      ],
      "notes": "经典的甜蜜诱惑",
      "cuisine": "甜点",
      "entry_date": "",
      "difficulty": 80,
      "makingTime": 40
    },
    {
      "id": "bk015",
      "name": "巧克力熔浆蛋糕",
      "category": "Bakery",
      "date": "2025-02",
      "rating": 5.0,
      "images": [
        "/images/bakery/bk015.jpg"
      ],
      "ingredients": [
        "糖 150g",
        "牛奶 400ml",
        "淡奶油 200ml",
        "鸡蛋 3个",
        "香草精"
      ],
      "steps": [
        "同上"
      ],
      "notes": "经典的甜蜜诱惑",
      "cuisine": "甜点",
      "entry_date": "",
      "difficulty": 80,
      "makingTime": 40
    },
    {
      "id": "bk016",
      "name": "巧克力熔浆蛋糕",
      "category": "Bakery",
      "date": "2025-02",
      "rating": 5.0,
      "images": [
        "/images/bakery/bk016.jpg"
      ],
      "ingredients": [
        "糖 150g",
        "牛奶 400ml",
        "淡奶油 200ml",
        "鸡蛋 3个",
        "香草精"
      ],
      "steps": [
        "同上"
      ],
      "notes": "经典的甜蜜诱惑",
      "cuisine": "甜点",
      "entry_date": "",
      "difficulty": 80,
      "makingTime": 40
    },
    {
      "id": "bk017",
      "name": "巧克力熔浆蛋糕",
      "category": "Bakery",
      "date": "2025-02",
      "rating": 5.0,
      "images": [
        "/images/bakery/bk017.jpg"
      ],
      "ingredients": [
        "糖 150g",
        "牛奶 400ml",
        "淡奶油 200ml",
        "鸡蛋 3个",
        "香草精"
      ],
      "steps": [
        "同上"
      ],
      "notes": "经典的甜蜜诱惑",
      "cuisine": "甜点",
      "entry_date": "",
      "difficulty": 80,
      "makingTime": 40
    },
    {
      "id": "bk018",
      "name": "巧克力熔浆蛋糕",
      "category": "Bakery",
      "date": "2025-03",
      "rating": 6.0,
      "images": [
        "/images/bakery/bk018-1.jpg",
        "/images/bakery/bk018-2.jpg",
        "/images/bakery/bk018-2.jpg",
        "/images/bakery/bk018-4.jpg",
        "/images/bakery/bk018-5.jpg",
        "/images/bakery/bk018-6.jpg",
        "/images/bakery/bk018-7.jpg",
        "/images/bakery/bk018-8.jpg"
      ],
      "ingredients": [
        "糖 150g",
        "牛奶 400ml",
        "淡奶油 200ml",
        "鸡蛋 3个",
        "香草精"
      ],
      "steps": [
        "同上"
      ],
      "notes": "经典的甜蜜诱惑",
      "cuisine": "甜点",
      "entry_date": "",
      "difficulty": 81,
      "makingTime": 41
    },
    {
      "id": "bk019",
      "name": "蜂蜜南瓜派",
      "category": "Bakery",
      "date": "2025-02",
      "rating": 4.0,
      "images": [
        "/images/bakery/bk019.jpg"
      ],
      "ingredients": [
        "糖 150g",
        "牛奶 400ml",
        "淡奶油 200ml",
        "鸡蛋 3个",
        "香草精"
      ],
      "steps": [
        "制作焦糖液倒入布丁杯",
        "加热牛奶和奶油",
        "鸡蛋打发加糖",
        "混合混合物",
        "水浴烤40分钟",
        "冷藏4小时"
      ],
      "notes": "温暖的南瓜香，完美的秋日下午茶",
      "cuisine": "甜点",
      "entry_date": "",
      "difficulty": 80,
      "makingTime": 70
    },
    {
      "id": "bk020",
      "name": "柠檬挞",
      "category": "Bakery",
      "date": "2025-02",
      "rating": 4.5,
      "images": [
        "/images/bakery/bk020.jpg"
      ],
      "ingredients": [
        "糖 150g",
        "牛奶 400ml",
        "淡奶油 200ml",
        "鸡蛋 3个",
        "香草精"
      ],
      "steps": [
        "制作焦糖液倒入布丁杯",
        "加热牛奶和奶油",
        "鸡蛋打发加糖",
        "混合混合物",
        "水浴烤40分钟",
        "冷藏4小时"
      ],
      "notes": "酸甜爽口，柠檬的清香在口中绽放",
      "cuisine": "甜点",
      "entry_date": "",
      "difficulty": 80,
      "makingTime": 45
    },
    {
      "id": "bk021",
      "name": "红丝绒纸杯蛋糕",
      "category": "Bakery",
      "date": "2025-01",
      "rating": 4.5,
      "images": [
        "/images/bakery/bk021.jpg"
      ],
      "ingredients": [
        "糖 150g",
        "牛奶 400ml",
        "淡奶油 200ml",
        "鸡蛋 3个",
        "香草精"
      ],
      "steps": [
        "制作焦糖液倒入布丁杯",
        "加热牛奶和奶油",
        "鸡蛋打发加糖",
        "混合混合物",
        "水浴烤40分钟",
        "冷藏4小时"
      ],
      "notes": "优雅的红色，甜而不腻的口感，很有质感",
      "cuisine": "甜点",
      "entry_date": "",
      "difficulty": 80,
      "makingTime": 55
    },
    {
      "id": "bk022",
      "name": "焦糖布丁",
      "category": "Bakery",
      "date": "2025-01",
      "rating": 4.0,
      "images": [
        "/images/bakery/bk022.jpg"
      ],
      "ingredients": [
        "糖 150g",
        "牛奶 400ml",
        "淡奶油 200ml",
        "鸡蛋 3个",
        "香草精"
      ],
      "steps": [
        "制作焦糖液倒入布丁杯",
        "加热牛奶和奶油",
        "鸡蛋打发加糖",
        "混合混合物",
        "水浴烤40分钟",
        "冷藏4小时"
      ],
      "notes": "焦糖的苦甜和蛋液的嫩滑完美平衡",
      "cuisine": "甜点",
      "entry_date": "",
      "difficulty": 80,
      "makingTime": 60
    },
    {
      "id": "bk023",
      "name": "开心果白巧克力饼干",
      "category": "Bakery",
      "date": "2025-01",
      "rating": 4.5,
      "images": [
        "/images/bakery/bk023.jpg"
      ],
      "ingredients": [
        "黄油 100g",
        "糖 80g",
        "鸡蛋 1个",
        "面粉 180g",
        "白巧克力块",
        "开心果"
      ],
      "steps": [
        "黄油和糖打发",
        "加入鸡蛋",
        "拌入面粉",
        "加入巧克力和坚果",
        "铺烤盘",
        "375°F烤12分钟"
      ],
      "notes": "香脆可口，白巧的甜和开心果的香很搭",
      "cuisine": "甜点",
      "entry_date": "",
      "difficulty": 80,
      "makingTime": 35
    },
    {
      "id": "bk024",
      "name": "抹茶白巧克力蛋糕卷",
      "category": "Bakery",
      "date": "2025-03",
      "rating": 5.0,
      "images": [
        "/images/bakery/bk024.jpg"
      ],
      "ingredients": [
        "鸡蛋 4个",
        "糖 60g",
        "面粉 50g",
        "抹茶粉 10g",
        "牛奶 40ml",
        "白巧克力",
        "淡奶油"
      ],
      "steps": [
        "蛋白蛋黄分离打发",
        "混合面粉和抹茶粉",
        "烤盘铺油纸倒入面糊",
        "350°F烤15分钟",
        "白巧克力奶油混合",
        "趁热卷起冷却"
      ],
      "notes": "抹茶的清苦配白巧的甜，层次丰富",
      "cuisine": "甜点",
      "entry_date": "",
      "difficulty": 80,
      "makingTime": 55
    },
    {
      "id": "bk025",
      "name": "樱桃马芬蛋糕",
      "category": "Bakery",
      "date": "2025-02",
      "rating": 4.0,
      "images": [
        "/images/bakery/bk025.jpg"
      ],
      "ingredients": [
        "面粉 200g",
        "糖 80g",
        "鸡蛋 2个",
        "牛奶 150ml",
        "黄油 80g",
        "新鲜樱桃",
        "泡打粉"
      ],
      "steps": [
        "黄油融化加糖和鸡蛋",
        "加入牛奶",
        "拌入面粉和泡打粉",
        "放入樱桃",
        "倒入马芬模",
        "350°F烤20分钟"
      ],
      "notes": "酸甜的樱桃融入蛋糕里，每一口都能吃到",
      "cuisine": "甜点",
      "entry_date": "",
      "difficulty": 80,
      "makingTime": 40
    },
    {
      "id": "bk026",
      "name": "黑森林蛋糕",
      "category": "Bakery",
      "date": "2025-03",
      "rating": 5.0,
      "images": [
        "/images/bakery/bk026.jpg"
      ],
      "ingredients": [
        "黑巧克力",
        "樱桃",
        "鲜奶油",
        "巧克力碎",
        "可可粉",
        "鸡蛋"
      ],
      "steps": [
        "烤巧克力蛋糕体",
        "樱桃去核准备",
        "打发鲜奶油",
        "组合蛋糕和奶油",
        "装饰巧克力碎和可可粉",
        "冷藏2小时"
      ],
      "notes": "经典的黑森林，华丽又不失优雅",
      "cuisine": "甜点",
      "entry_date": "",
      "difficulty": 80,
      "makingTime": 120
    }
  ]
}